pyheap/__init__.py
pyheap/heap.py
winheap/__init__.py
winheap/heap.py
winheap/_raw/__init__.py
winheap/_raw/heapapi.py
winheap/_raw/minwinbase.py
winheap/_raw/winnt.py
winheap-1.4.0.dist-info/METADATA
winheap-1.4.0.dist-info/WHEEL
winheap-1.4.0.dist-info/top_level.txt
winheap-1.4.0.dist-info/RECORD
