Metadata-Version: 2.4
Name: winheap
Version: 1.4.0
Summary: Exposes windows heap features like HeapCreate
Author-email: WCG847 <heelmods@gmail.com>
License-Expression: GPL-3.0-or-later
Keywords: heap,memory,raw,ruthless,unforgiving,windows,technical,win32
Platform: Windows
Classifier: Development Status :: 5 - Production/Stable
Classifier: Environment :: Win32 (MS Windows)
Classifier: Intended Audience :: Developers
Classifier: Natural Language :: English
Classifier: Operating System :: Microsoft :: Windows :: Windows 11
Classifier: Programming Language :: Python :: Free Threading :: 3 - Stable
Classifier: Topic :: System :: Hardware
Classifier: Typing :: Typed
Requires-Python: >=3.14
